quickdump/__init__.py
quickdump/const.py
quickdump/dumper.py
quickdump/server_http.py
quickdump/server_tcp.py
quickdump/tests/__init__.py
quickdump/tests/some_other_label.qd
quickdump/tests/test_example.py
quickdump/utils.py
quickdump-0.5.0.dist-info/entry_points.txt
quickdump-0.5.0.dist-info/WHEEL
quickdump-0.5.0.dist-info/METADATA
quickdump-0.5.0.dist-info/RECORD
