Metadata-Version: 2.1
Name: quickdump
Version: 0.5.0
Summary: Quickly store arbitrary Python objects in unique files.
Home-page: https://github.com/pedrovhb/quickdump
License: MIT
Keywords: quickdump,dump,serialize,store
Author: Pedro Batista
Author-email: pedrovhb@gmail.com
Requires-Python: >=3.7,<4.0
Classifier: License :: OSI Approved :: MIT License
Classifier: Programming Language :: Python :: 3
Classifier: Programming Language :: Python :: 3.10
Classifier: Programming Language :: Python :: 3.7
Classifier: Programming Language :: Python :: 3.8
Classifier: Programming Language :: Python :: 3.9
Requires-Dist: dill (>=0.3.4,<0.4.0)
Requires-Dist: loguru (>=0.6.0,<0.7.0)
Requires-Dist: lz4 (>=4.0.0,<5.0.0)
Requires-Dist: multidict (>=6.0.2,<7.0.0)
Requires-Dist: starlette[server] (>=0.19.0,<0.20.0)
Requires-Dist: uvicorn[server] (>=0.17.6,<0.18.0)
Project-URL: Repository, https://github.com/pedrovhb/quickdump
